trinary.py
trinary-0.2.0.dist-info/LICENSE.md
trinary-0.2.0.dist-info/WHEEL
trinary-0.2.0.dist-info/METADATA
trinary-0.2.0.dist-info/RECORD
