Metadata-Version: 2.1
Name: trinary
Version: 0.2.0
Summary: Trinary logic in Python
Author: Travis Jungroth
Author-email: jungroth@gmail.com
Requires-Python: >=3.9,<4.0
Classifier: Programming Language :: Python :: 3
Classifier: Programming Language :: Python :: 3.9
Classifier: Programming Language :: Python :: 3.10
Classifier: Programming Language :: Python :: 3.11
